README.rst
setup.py
src/zc/__init__.py
src/zc.sqs.egg-info/PKG-INFO
src/zc.sqs.egg-info/SOURCES.txt
src/zc.sqs.egg-info/dependency_links.txt
src/zc.sqs.egg-info/entry_points.txt
src/zc.sqs.egg-info/namespace_packages.txt
src/zc.sqs.egg-info/not-zip-safe
src/zc.sqs.egg-info/requires.txt
src/zc.sqs.egg-info/top_level.txt
src/zc/sqs/README.rst
src/zc/sqs/__init__.py
src/zc/sqs/testing.py
src/zc/sqs/tests.py