Metadata-Version: 1.0
Name: zc.sqs
Version: 0.2.1
Summary: ==================
Home-page: UNKNOWN
Author: Jim Fulton
Author-email: jim@zope.com
License: ZPL 2.1
Platform: UNKNOWN
